<annotation>
  <folder>D:\dataenhance\newflaw\imgs\enhanceflawimg</folder>
  <filename>177_2_1.jpg</filename>
  <path>D:\dataenhance\newflaw\imgs\enhanceflawimg\177_2_1.jpg</path>
  <source>
    <database>Unknown</database>
  </source>
  <size>
    <width>1653</width>
    <height>721</height>
    <depth>3</depth>
  </size>
  <segmented>0</segmented>
  <object>
    <name>flaw</name>
    <pose>Unspecified</pose>
    <truncated>0</truncated>
    <difficult>0</difficult>
    <bndbox>
      <xmin>1014</xmin>
      <ymin>68</ymin>
      <xmax>1449</xmax>
      <ymax>149</ymax>
    </bndbox>
  </object>
</annotation>
